active_arc/README.md
active_arc/__init__.py
active_arc/agent.py
active_arc/recorder.py
active_arc/structs.py
active_arc/swarm.py
active_arc/tracing.py
active_arc/templates/__init__.py
active_arc/templates/llm_agent.py
active_arc/templates/random_agent.py
active_arc-0.1.1.dist-info/METADATA
active_arc-0.1.1.dist-info/WHEEL
active_arc-0.1.1.dist-info/licenses/LICENSE
active_arc-0.1.1.dist-info/RECORD
