Metadata-Version: 2.4
Name: active-arc
Version: 0.1.1
Summary: Active-ARC Agents
License-File: LICENSE
Requires-Python: >=3.10
Requires-Dist: openai>=1.0.0
Requires-Dist: pydantic>=2.0.0
Requires-Dist: python-dotenv>=1.0.0
Requires-Dist: requests>=2.32.0
Provides-Extra: agentops
Requires-Dist: agentops>=0.4.18; extra == 'agentops'
